splunk_toolbox/__init__.py
splunk_toolbox-1.2.0.data/scripts/splunktoolbox
splunk_toolbox-1.2.0.dist-info/METADATA
splunk_toolbox-1.2.0.dist-info/WHEEL
splunk_toolbox-1.2.0.dist-info/top_level.txt
splunk_toolbox-1.2.0.dist-info/RECORD
