Metadata-Version: 2.1
Name: splunk-toolbox
Version: 1.2.0
Summary: A wrapper around the Splunk REST API endpoint
Home-page: https://github.com/gnubyte/splunk-toolbox
Author: Patrick Hastings
Author-email: phastings@openmobo.com
License: UNKNOWN
Platform: UNKNOWN
Classifier: Programming Language :: Python :: 3
Classifier: License :: OSI Approved :: MIT License
Classifier: Operating System :: OS Independent
Requires-Dist: requests
